servefile/__init__.py
servefile/__main__.py
servefile/servefile.py
servefile-0.5.4.dist-info/METADATA
servefile-0.5.4.dist-info/WHEEL
servefile-0.5.4.dist-info/entry_points.txt
servefile-0.5.4.dist-info/top_level.txt
servefile-0.5.4.dist-info/RECORD
